[
    {
        "image": [
            "./Tekalne steze - Ceneje.si_files/eNdKx1qRAvpj"
        ],
        "title": "KLARFIT steza za tek Pacemaker X3, črna",
        "min_price": "354,00 €",
        "stores": "",
        "action": "V trgovino"
    },
    {
        "image": [
            "./Tekalne steze - Ceneje.si_files/zBxwEIuny0vJ"
        ],
        "title": "KLARFIT steza za tek Pacemaker X1, črna",
        "min_price": "271,00 €",
        "stores": "",
        "action": "V trgovino"
    },
    {
        "image": [
            "./Tekalne steze - Ceneje.si_files/HDp2uysPoJ5"
        ],
        "title": "KOOLOOK zložljiva magnetna tekalna steza (primerna za hujšanje)",
        "min_price": "119,90 €",
        "stores": "v MEGA FITNESS",
        "action": "V trgovino"
    },
    {
        "image": [
            "./Tekalne steze - Ceneje.si_files/oSpVKQSwm37G"
        ],
        "title": "INSPORTLINE magnetna tekalna steza Sprynkl",
        "min_price": "199,90 €",
        "stores": "v Insportline.si",
        "action": "V trgovino"
    },
    {
        "image": [
            "./Tekalne steze - Ceneje.si_files/8mPgLd32yTuE"
        ],
        "title": "INSPORTLINE tekalna steza Lavister",
        "min_price": "506,10 €",
        "stores": "v 2 trgovinah",
        "action": "Več o ponudbi"
    },
    {
        "image": [
            "./Tekalne steze - Ceneje.si_files/LuioE3FnQjuK"
        ],
        "title": "KLARFIT Highflyer 2.0, tekalna steza, 2.0 PS, 4P-AntiShock Suspension  (FIT18-Highfly2)",
        "min_price": "573,00 €",
        "stores": "v Electronic star",
        "action": "V trgovino"
    },
    {
        "image": [
            "./Tekalne steze - Ceneje.si_files/g6fcJZbiOGJO"
        ],
        "title": "KOOLOOK zložljiva magnetna tekalna steza, primerna za hujšanje",
        "min_price": "109,90 €",
        "stores": "v MEGA FITNESS",
        "action": "V trgovino"
    },
    {
        "image": [
            "./Tekalne steze - Ceneje.si_files/UPiu0oVN8LQc"
        ],
        "title": "Klarfit   (FIT18-Treado Advance)",
        "min_price": "312,00 €",
        "stores": "v Electronic star",
        "action": "V trgovino"
    },
    {
        "image": [
            "./Tekalne steze - Ceneje.si_files/wQ6PgnOMMLKO"
        ],
        "title": "INSPORTLINE tekalna steza EXCEL RUN",
        "min_price": "269,90 €",
        "stores": "v Insportline.si",
        "action": "V trgovino"
    },
    {
        "image": [
            "./Tekalne steze - Ceneje.si_files/eNdKx1qRAvpj"
        ],
        "title": "KLARFIT steza za tek Pacemaker X3, črna",
        "min_price": "354,00 €",
        "stores": "v Electronic star",
        "action": "V trgovino"
    },
    {
        "image": [
            "./Tekalne steze - Ceneje.si_files/3oQ4IQuS48NX"
        ],
        "title": "CAPITAL SPORTS tekalna steza Infinity Track 2.0",
        "min_price": "729,00 €",
        "stores": "v Electronic star",
        "action": "V trgovino"
    },
    {
        "image": [
            "./Tekalne steze - Ceneje.si_files/oQC8WdsDxhHx"
        ],
        "title": "KLARFIT Treado Active, tekalna steza, 1 HP, 10 km/u, 36 x 100 cm, bluetooth, zaslon na dotik (FITN15-TreadoActive)",
        "min_price": "354,00 €",
        "stores": "v Electronic star",
        "action": "V trgovino"
    },
    {
        "image": [
            "./Tekalne steze - Ceneje.si_files/PgLoShYvbvk"
        ],
        "title": "KLARFIT Treado Sport 2.0, tekalna steza, 2,0 HP, samomazalni sistem 3-Level InclineSystem (FIT18-TreadoSport2.0)",
        "min_price": "521,00 €",
        "stores": "v Electronic star",
        "action": "V trgovino"
    },
    {
        "image": [
            "./Tekalne steze - Ceneje.si_files/qYoRVDztuseo"
        ],
        "title": "KETTLER tekalna steza TRACK S4",
        "min_price": "989,90 €",
        "stores": "v sportnaoprema.si",
        "action": "V trgovino"
    },
    {
        "image": [
            "./Tekalne steze - Ceneje.si_files/zBxwEIuny0vJ"
        ],
        "title": "KLARFIT steza za tek Pacemaker X1, črna",
        "min_price": "271,00 €",
        "stores": "v Electronic star",
        "action": "V trgovino"
    },
    {
        "image": [
            "./Tekalne steze - Ceneje.si_files/uwCX0yTOFzO"
        ],
        "title": "Klarfit (Workspace_go_tablet)",
        "min_price": "385,00 €",
        "stores": "v Electronic star",
        "action": "V trgovino"
    },
    {
        "image": [
            "./Tekalne steze - Ceneje.si_files/4e3uERW6LFdk"
        ],
        "title": "CAPITAL tekalna steza SPORTS",
        "min_price": "969,00 €",
        "stores": "v Electronic star",
        "action": "V trgovino"
    },
    {
        "image": [
            "./Tekalne steze - Ceneje.si_files/pP2WqZ04FNY1"
        ],
        "title": "Tekalna steza Diadora z avtomatičnim naklonom Edge 2.0 dark",
        "min_price": "529,00 €",
        "stores": "v Timebreak.eu",
        "action": "V trgovino"
    },
    {
        "image": [
            "./Tekalne steze - Ceneje.si_files/mSJTkpN1nlH8"
        ],
        "title": "X Fact tekalna stezat HAMBURG S 12",
        "min_price": "599,99 €",
        "stores": "v Hervis",
        "action": "V trgovino"
    },
    {
        "image": [
            "./Tekalne steze - Ceneje.si_files/pbNSW7mc7C7q"
        ],
        "title": "DIADORA tekalna steza STAR 1000 z naklonom",
        "min_price": "369,00 €",
        "stores": "v Timebreak.eu",
        "action": "V trgovino"
    },
    {
        "image": [
            "./Tekalne steze - Ceneje.si_files/XZjoBUsuOu7R"
        ],
        "title": "Body Sculpture BT 5408S3BPC tekalna steza",
        "min_price": "579,90 €",
        "stores": "v mimovrste=)",
        "action": "V trgovino"
    },
    {
        "image": [
            "./Tekalne steze - Ceneje.si_files/va8sKQQKL2qM"
        ],
        "title": "Klarfit   (VPT2-WKSPACE GO)",
        "min_price": "364,00 €",
        "stores": "v Electronic star",
        "action": "V trgovino"
    },
    {
        "image": [
            "./Tekalne steze - Ceneje.si_files/dyppXwMKP2J"
        ],
        "title": "Capital Sports Pacemaker F80, tekalna steza, 3 HP, 14 km/h, 4P-AntiShock Suspension, USB (FIT7-PaceMKR-F80)",
        "min_price": "677,00 €",
        "stores": "v Electronic star",
        "action": "V trgovino"
    },
    {
        "image": [
            "./Tekalne steze - Ceneje.si_files/afgtYhWYwSJq"
        ],
        "title": "Tekalna steza Track S6 Kettler",
        "min_price": "1.399,00 €",
        "stores": "v sportnaoprema.si",
        "action": "V trgovino"
    },
    {
        "image": [
            "./Tekalne steze - Ceneje.si_files/buVPn1xSEaAu"
        ],
        "title": "Tekalna steza NordicTrack X32i – incline trainer",
        "min_price": "3.999,00 €",
        "stores": "v sportnaoprema.si",
        "action": "V trgovino"
    },
    {
        "image": [
            "./Tekalne steze - Ceneje.si_files/pgMQQ8UDnZ5r"
        ],
        "title": "Profesionalna tekaška steza TRX-3000 Toorx HIGH FLEX DECK",
        "min_price": "2.298,96 €",
        "stores": "v 2 trgovinah",
        "action": "Več o ponudbi"
    },
    {
        "image": [
            "./Tekalne steze - Ceneje.si_files/Z7cy6QEzWeoH"
        ],
        "title": "INSPORTLINE tekalna steza inCondi T40i",
        "min_price": "806,60 €",
        "stores": "v Insportline.si",
        "action": "V trgovino"
    }
]